VKPy/__init__.py
VKPy-0.1.1.dist-info/DESCRIPTION.rst
VKPy-0.1.1.dist-info/METADATA
VKPy-0.1.1.dist-info/RECORD
VKPy-0.1.1.dist-info/WHEEL
VKPy-0.1.1.dist-info/metadata.json
VKPy-0.1.1.dist-info/top_level.txt
