Metadata-Version: 2.0
Name: VKPy
Version: 0.1.1
Summary: VK bot development micro framework
Home-page: https://github.com/irdkwmnsb/VKPy
Author: irdkwmnsb
Author-email: me@alzhanov.ru
License: UNKNOWN
Platform: UNKNOWN
Classifier: Programming Language :: Python :: 3
Classifier: License :: OSI Approved :: MIT License
Classifier: Operating System :: OS Independent
Requires-Dist: requests
Requires-Dist: vk
